jsonlog_cli/__init__.py
jsonlog_cli/__main__.py
jsonlog_cli/cli.py
jsonlog_cli/colours.py
jsonlog_cli/config.py
jsonlog_cli/pattern.py
jsonlog_cli/record.py
jsonlog_cli/stream.py
jsonlog_cli/tests/__init__.py
jsonlog_cli/tests/test_record.py
jsonlog_cli/text.py
jsonlog_cli/types.py
jsonlog_cli-6.3.0.dist-info/entry_points.txt
jsonlog_cli-6.3.0.dist-info/WHEEL
jsonlog_cli-6.3.0.dist-info/METADATA
jsonlog_cli-6.3.0.dist-info/RECORD
