Metadata-Version: 2.1
Name: jsonlog-cli
Version: 6.3.0
Summary: Convert structured JSON logs to human-readable output
Home-page: https://github.com/borntyping/jsonlog/tree/master/jsonlog-cli
License: MIT
Author: Sam Clements
Author-email: sam@borntyping.co.uk
Requires-Python: >=3.6,<4.0
Classifier: License :: OSI Approved :: MIT License
Classifier: Programming Language :: Python :: 3
Classifier: Programming Language :: Python :: 3.6
Classifier: Programming Language :: Python :: 3.7
Classifier: Programming Language :: Python :: 3.8
Requires-Dist: click
Requires-Dist: jsonlog
Requires-Dist: pydantic (>=1.5.1,<1.6.0)
Requires-Dist: typing-extensions
Requires-Dist: xdg
Project-URL: Repository, https://github.com/borntyping/jsonlog
